gospl/__init__.py
gospl/model.py
gospl/flow/__init__.py
gospl/flow/flowplex.py
gospl/mesher/__init__.py
gospl/mesher/unstructuredmesh.py
gospl/sed/__init__.py
gospl/sed/sedplex.py
gospl/tools/__init__.py
gospl/tools/inputparser.py
gospl/tools/outmesh.py
gospl-0.1.12.dist-info/LICENSE
gospl-0.1.12.dist-info/METADATA
gospl-0.1.12.dist-info/WHEEL
gospl-0.1.12.dist-info/top_level.txt
gospl-0.1.12.dist-info/RECORD
