Metadata-Version: 2.1
Name: gospl
Version: 0.1.12
Summary: A Python interface to perform Global Landscape Evolution Model
Home-page: https://github.com/Geodels/gospl
Author: Tristan Salles  
Author-email: tristan.salles@sydney.edu.au
License: UNKNOWN
Platform: UNKNOWN
Classifier: Programming Language :: Python :: 3.5
Classifier: Programming Language :: Python :: 3.6
Classifier: Programming Language :: Python :: 3.7
Classifier: Programming Language :: Python :: 3.8
Requires-Python: >=3.3
Requires-Dist: pytest
Requires-Dist: Cython (==0.29.21)
Requires-Dist: numpy (==1.19.2)
Requires-Dist: scipy (==1.5.2)
Requires-Dist: h5py (==2.10.0)
Requires-Dist: pandas (==1.1.2)
Requires-Dist: ruamel.yaml (==0.16.12)
Requires-Dist: meshplex (==0.13.3)
Requires-Dist: mpi4py (>=3.0.3)
Requires-Dist: petsc4py (>=3.13.0)
Requires-Dist: pre-commit (==2.7.1)
Requires-Dist: fastfunc (==0.2.3)
Requires-Dist: vtk (>=9.0.0)
Requires-Dist: numpy-indexed (==0.3.5)
Requires-Dist: meshio (==4.2.0)
Requires-Dist: scikit-fuzzy (>=0.4.2)
